probed/__init__.py
probed/__main__.py
probed/hooking/__init__.py
probed/hooking/ante_build_hook.py
probed/hooking/ante_release_hook.py
probed/hooking/post_build_hook.py
probed/hooking/post_release_hook.py
probed/pyrustic_data/build_report.json
probed/pyrustic_data/hooking.json
probed/pyrustic_data/hubstore.json
probed/pyrustic_data/release_info.json
probed/pyrustic_data/backstage/config/build.json
probed/pyrustic_data/backstage/config/init.json
probed/pyrustic_data/backstage/config/release.json
probed/pyrustic_data/backstage/data/build_report.json
probed/pyrustic_data/backstage/data/github_release_form.json
probed/pyrustic_data/backstage/hooking/build.json
probed/pyrustic_data/backstage/hooking/init.json
probed/pyrustic_data/backstage/hooking/release.json
probed/pyrustic_data/backstage/report/build_report.json
probed/pyrustic_data/backstage/report/release_report.json
probed/pyrustic_data/hubstore/img.json
probed/pyrustic_data/hubstore/promotion.json
secret/SCRATCH.py
secret/__init__.py
tests/__init__.py
tests/__main__.py
probed-0.0.11.dist-info/LICENSE
probed-0.0.11.dist-info/METADATA
probed-0.0.11.dist-info/WHEEL
probed-0.0.11.dist-info/entry_points.txt
probed-0.0.11.dist-info/top_level.txt
probed-0.0.11.dist-info/RECORD
