Metadata-Version: 2.1
Name: probed
Version: 0.0.11
Summary: Probed collections
Home-page: https://github.com/pyrustic/probed
Author: Pyrustic Evangelist
Author-email: rusticalex@yahoo.com
Maintainer: Pyrustic Evangelist
Maintainer-email: rusticalex@yahoo.com
License: MIT
Keywords: library,collections,notification,change-tracking,dict,set,list,containers,probed-dict,probed-set,probed-list,lightweight,pyrustic
Platform: UNKNOWN
Classifier: Programming Language :: Python :: 3
Classifier: License :: OSI Approved :: MIT License
Classifier: Operating System :: OS Independent
Requires-Python: >=3.5
License-File: LICENSE
